dblogger/format.py
dblogger/logger.py
dblogger/query.py
dblogger/utils.py
dblogger/__init__.py
dblogger/configure.py
dblogger/tests/test_dblogger_throughput.py
dblogger/tests/__init__.py
dblogger/tests/test_dblogger.py
dblogger/tests/test_configure.py
dblogger-0.4.1.data/scripts/dblogger
dblogger-0.4.1.dist-info/RECORD
dblogger-0.4.1.dist-info/top_level.txt
dblogger-0.4.1.dist-info/WHEEL
dblogger-0.4.1.dist-info/METADATA
dblogger-0.4.1.dist-info/pydist.json
dblogger-0.4.1.dist-info/DESCRIPTION.rst
dblogger-0.4.1.dist-info/entry_points.txt
