Metadata-Version: 2.0
Name: dblogger
Version: 0.4.1
Summary: DB-backed python logging.Handler subclass that uses kvlayer, and provides command-line tools.
Home-page: https://github.com/diffeo/dblogger
Author: Diffeo, Inc.
Author-email: support@diffeo.com
License: MIT/X11 license http://opensource.org/licenses/MIT
Platform: UNKNOWN
Classifier: Development Status :: 3 - Alpha
Classifier: Topic :: Utilities
Classifier: License :: OSI Approved :: MIT License
Requires-Dist: yakonfig (>=0.4.1)
Requires-Dist: kvlayer (>=0.4.0)
Requires-Dist: streamcorpus
Requires-Dist: python-dateutil
